sand_drepr/__init__.py
sand_drepr/drepr-old/__init__.py
sand_drepr/drepr-old/main.py
sand_drepr/drepr-old/resources.py
sand_drepr/drepr-old/semanticmodel.py
sand_drepr/drepr-old/transformation.py
sand_drepr/dreprmodel.py
sand_drepr/main.py
sand_drepr/raw_transformations/__init__.py
sand_drepr/raw_transformations/decimal_number.py
sand_drepr/raw_transformations/global_coordinate.py
sand_drepr/raw_transformations/integer_number.py
sand_drepr/raw_transformations/number.py
sand_drepr/raw_transformations/uri.py
sand_drepr/resources.py
sand_drepr/semanticmodel.py
sand_drepr/transformation.py
sand_drepr-1.0.3.dist-info/METADATA
sand_drepr-1.0.3.dist-info/WHEEL
sand_drepr-1.0.3.dist-info/RECORD
